{
	"info": {
		"_postman_id": "12d843e5-7c4a-4e84-855a-0a120edbe487",
		"name": "Authentication",
		"schema": "https://schema.getpostman.com/json/collection/v2.1.0/collection.json"
	},
	"item": [
		{
			"name": "Create user user1",
			"event": [
				{
					"listen": "test",
					"script": {
						"id": "277e62d2-609a-45fa-a256-5290a00398a6",
						"exec": [
							"pm.test(\"Status code is 200\", function () {",
							"    pm.response.to.have.status(200);",
							"});"
						],
						"type": "text/javascript"
					}
				}
			],
			"request": {
				"method": "POST",
				"header": [
					{
						"key": "Content-Type",
						"name": "Content-Type",
						"value": "application/json",
						"type": "text"
					}
				],
				"body": {
					"mode": "raw",
					"raw": "{\n\t\"username\" : \"user1\",\n\t\"password\" : \"password1\"\n}"
				},
				"url": {
					"raw": "{{host}}/user",
					"host": [
						"{{host}}"
					],
					"path": [
						"user"
					]
				}
			},
			"response": []
		},
		{
			"name": "Authenticate as user1",
			"event": [
				{
					"listen": "test",
					"script": {
						"id": "4b10362d-8346-470b-88e4-5d9a2acf0ea4",
						"exec": [
							"pm.test(\"Status code is 200\", function () {",
							"    pm.response.to.have.status(200);",
							"});"
						],
						"type": "text/javascript"
					}
				}
			],
			"request": {
				"auth": {
					"type": "noauth"
				},
				"method": "POST",
				"header": [
					{
						"key": "Content-Type",
						"name": "Content-Type",
						"value": "application/json",
						"type": "text"
					}
				],
				"body": {
					"mode": "raw",
					"raw": "{\n\t\"username\" : \"user1\",\n\t\"password\" : \"password1\"\n}"
				},
				"url": {
					"raw": "{{host}}/authentication",
					"host": [
						"{{host}}"
					],
					"path": [
						"authentication"
					]
				}
			},
			"response": []
		},
		{
			"name": "Create user user2",
			"event": [
				{
					"listen": "test",
					"script": {
						"id": "f8f6e163-ed51-4807-aa29-e8630fb160e4",
						"exec": [
							"pm.test(\"Status code is 200\", function () {",
							"    pm.response.to.have.status(200);",
							"});"
						],
						"type": "text/javascript"
					}
				}
			],
			"request": {
				"method": "POST",
				"header": [
					{
						"key": "Content-Type",
						"name": "Content-Type",
						"type": "text",
						"value": "application/json"
					}
				],
				"body": {
					"mode": "raw",
					"raw": "{\n\t\"username\" : \"user2\",\n\t\"password\" : \"password2\"\n}"
				},
				"url": {
					"raw": "{{host}}/user",
					"host": [
						"{{host}}"
					],
					"path": [
						"user"
					]
				}
			},
			"response": []
		},
		{
			"name": "Authenticate as user2",
			"event": [
				{
					"listen": "test",
					"script": {
						"id": "25f57df3-c53e-4062-9037-6cf50420099d",
						"exec": [
							"pm.test(\"Status code is 200\", function () {",
							"    pm.response.to.have.status(200);",
							"});"
						],
						"type": "text/javascript"
					}
				}
			],
			"request": {
				"auth": {
					"type": "noauth"
				},
				"method": "POST",
				"header": [
					{
						"key": "Content-Type",
						"name": "Content-Type",
						"type": "text",
						"value": "application/json"
					}
				],
				"body": {
					"mode": "raw",
					"raw": "{\n\t\"username\" : \"user2\",\n\t\"password\" : \"password2\"\n}"
				},
				"url": {
					"raw": "{{host}}/authentication",
					"host": [
						"{{host}}"
					],
					"path": [
						"authentication"
					]
				}
			},
			"response": []
		},
		{
			"name": "Attempt to change user1's password as non-admin",
			"event": [
				{
					"listen": "test",
					"script": {
						"id": "dd89ebf4-0cb9-42c6-8191-b515b39d6f9e",
						"exec": [
							"pm.test(\"Status code is 401\", function () {",
							"    pm.response.to.have.status(401);",
							"});"
						],
						"type": "text/javascript"
					}
				}
			],
			"request": {
				"auth": {
					"type": "basic",
					"basic": [
						{
							"key": "password",
							"value": "password2",
							"type": "string"
						},
						{
							"key": "username",
							"value": "user2",
							"type": "string"
						}
					]
				},
				"method": "POST",
				"header": [
					{
						"key": "Content-Type",
						"name": "Content-Type",
						"type": "text",
						"value": "application/json"
					}
				],
				"body": {
					"mode": "raw",
					"raw": "{\n\t\"username\" : \"user1\",\n\t\"password\" : \"password2\"\n}"
				},
				"url": {
					"raw": "{{host}}/password",
					"host": [
						"{{host}}"
					],
					"path": [
						"password"
					]
				}
			},
			"response": []
		},
		{
			"name": "Attempt to change user1's password as admin",
			"event": [
				{
					"listen": "test",
					"script": {
						"id": "8a550e7a-054f-4ae7-a7cd-2f3812642b5f",
						"exec": [
							"pm.test(\"Status code is 200\", function () {",
							"    pm.response.to.have.status(200);",
							"});"
						],
						"type": "text/javascript"
					}
				}
			],
			"request": {
				"method": "POST",
				"header": [
					{
						"key": "Content-Type",
						"name": "Content-Type",
						"type": "text",
						"value": "application/json"
					}
				],
				"body": {
					"mode": "raw",
					"raw": "{\n\t\"username\" : \"user1\",\n\t\"password\" : \"password2\"\n}"
				},
				"url": {
					"raw": "{{host}}/password",
					"host": [
						"{{host}}"
					],
					"path": [
						"password"
					]
				}
			},
			"response": []
		},
		{
			"name": "Authenticate as user1 with new password",
			"event": [
				{
					"listen": "test",
					"script": {
						"id": "586e46da-5ff7-49bf-9f6d-049ad5414477",
						"exec": [
							"pm.test(\"Status code is 200\", function () {",
							"    pm.response.to.have.status(200);",
							"});"
						],
						"type": "text/javascript"
					}
				}
			],
			"request": {
				"auth": {
					"type": "noauth"
				},
				"method": "POST",
				"header": [
					{
						"key": "Content-Type",
						"name": "Content-Type",
						"type": "text",
						"value": "application/json"
					}
				],
				"body": {
					"mode": "raw",
					"raw": "{\n\t\"username\" : \"user1\",\n\t\"password\" : \"password2\"\n}"
				},
				"url": {
					"raw": "{{host}}/authentication",
					"host": [
						"{{host}}"
					],
					"path": [
						"authentication"
					]
				}
			},
			"response": []
		},
		{
			"name": "Attempt to change user1's password as user1",
			"event": [
				{
					"listen": "test",
					"script": {
						"id": "834b33fc-7f6b-447f-b7d8-8a952b740ecd",
						"exec": [
							"pm.test(\"Status code is 200\", function () {",
							"    pm.response.to.have.status(200);",
							"});"
						],
						"type": "text/javascript"
					}
				}
			],
			"request": {
				"auth": {
					"type": "basic",
					"basic": [
						{
							"key": "username",
							"value": "user1",
							"type": "string"
						},
						{
							"key": "password",
							"value": "password2",
							"type": "string"
						}
					]
				},
				"method": "POST",
				"header": [
					{
						"key": "Content-Type",
						"name": "Content-Type",
						"type": "text",
						"value": "application/json"
					}
				],
				"body": {
					"mode": "raw",
					"raw": "{\n\t\"username\" : \"user1\",\n\t\"password\" : \"password3\"\n}"
				},
				"url": {
					"raw": "{{host}}/password",
					"host": [
						"{{host}}"
					],
					"path": [
						"password"
					]
				}
			},
			"response": []
		},
		{
			"name": "Authenticate as user1 with new password",
			"event": [
				{
					"listen": "test",
					"script": {
						"id": "20ff1b1e-811d-43ee-a26c-15cfa77dcf99",
						"exec": [
							"pm.test(\"Status code is 200\", function () {",
							"    pm.response.to.have.status(200);",
							"});"
						],
						"type": "text/javascript"
					}
				}
			],
			"request": {
				"auth": {
					"type": "noauth"
				},
				"method": "POST",
				"header": [
					{
						"key": "Content-Type",
						"name": "Content-Type",
						"type": "text",
						"value": "application/json"
					}
				],
				"body": {
					"mode": "raw",
					"raw": "{\n\t\"username\" : \"user1\",\n\t\"password\" : \"password3\"\n}"
				},
				"url": {
					"raw": "{{host}}/authentication",
					"host": [
						"{{host}}"
					],
					"path": [
						"authentication"
					]
				}
			},
			"response": []
		},
		{
			"name": "Attempt to change unknown user's password as admin",
			"event": [
				{
					"listen": "test",
					"script": {
						"id": "e45c1551-a955-4d3a-8ff2-217f66a81db8",
						"exec": [
							"pm.test(\"Status code is 404\", function () {",
							"    pm.response.to.have.status(404);",
							"});"
						],
						"type": "text/javascript"
					}
				}
			],
			"request": {
				"auth": {
					"type": "basic",
					"basic": [
						{
							"key": "password",
							"value": "test",
							"type": "string"
						},
						{
							"key": "username",
							"value": "test",
							"type": "string"
						}
					]
				},
				"method": "POST",
				"header": [
					{
						"key": "Content-Type",
						"name": "Content-Type",
						"type": "text",
						"value": "application/json"
					}
				],
				"body": {
					"mode": "raw",
					"raw": "{\n\t\"username\" : \"user3\",\n\t\"password\" : \"password1\"\n}"
				},
				"url": {
					"raw": "{{host}}/password",
					"host": [
						"{{host}}"
					],
					"path": [
						"password"
					]
				}
			},
			"response": []
		},
		{
			"name": "Attempt to change unknown user's password as non-admin",
			"event": [
				{
					"listen": "test",
					"script": {
						"id": "dd728e87-bf11-4991-a09e-0f5dd0bf0783",
						"exec": [
							"pm.test(\"Status code is 401\", function () {",
							"    pm.response.to.have.status(401);",
							"});"
						],
						"type": "text/javascript"
					}
				}
			],
			"request": {
				"auth": {
					"type": "basic",
					"basic": [
						{
							"key": "password",
							"value": "password2",
							"type": "string"
						},
						{
							"key": "username",
							"value": "user2",
							"type": "string"
						}
					]
				},
				"method": "POST",
				"header": [
					{
						"key": "Content-Type",
						"name": "Content-Type",
						"type": "text",
						"value": "application/json"
					}
				],
				"body": {
					"mode": "raw",
					"raw": "{\n\t\"username\" : \"user3\",\n\t\"password\" : \"password1\"\n}"
				},
				"url": {
					"raw": "{{host}}/password",
					"host": [
						"{{host}}"
					],
					"path": [
						"password"
					]
				}
			},
			"response": []
		}
	],
	"auth": {
		"type": "bearer"
	},
	"event": [
		{
			"listen": "prerequest",
			"script": {
				"id": "9719183c-3fdb-46e0-ba4f-28c75b9220ec",
				"type": "text/javascript",
				"exec": [
					""
				]
			}
		},
		{
			"listen": "test",
			"script": {
				"id": "5eced19e-077a-4208-ac4a-98549e1b024a",
				"type": "text/javascript",
				"exec": [
					""
				]
			}
		}
	]
}